Makefile
README.txt
setup.cfg
setup.py
docs/HISTORY.txt
haufe/__init__.py
haufe.sharepoint.egg-info/PKG-INFO
haufe.sharepoint.egg-info/SOURCES.txt
haufe.sharepoint.egg-info/dependency_links.txt
haufe.sharepoint.egg-info/entry_points.txt
haufe.sharepoint.egg-info/namespace_packages.txt
haufe.sharepoint.egg-info/not-zip-safe
haufe.sharepoint.egg-info/requires.txt
haufe.sharepoint.egg-info/top_level.txt
haufe/sharepoint/__init__.py
haufe/sharepoint/cli.py
haufe/sharepoint/connector.py
haufe/sharepoint/example.py
haufe/sharepoint/logger.py
haufe/sharepoint/patches.py
haufe/sharepoint/misc/full_soap.log
haufe/sharepoint/tests/__init__.py
haufe/sharepoint/tests/test_connector.py